dbman/__init__.py
dbman/__version__.py
dbman/api.py
dbman/cli.py
dbman/core.py
dbman/enum.py
dbman/error.py
dbman/log.py
dbman/config/base_config.py
dbman/config/dbman_logging.json
dbman-0.0.2.dist-info/LICENSE
dbman-0.0.2.dist-info/METADATA
dbman-0.0.2.dist-info/WHEEL
dbman-0.0.2.dist-info/entry_points.txt
dbman-0.0.2.dist-info/top_level.txt
dbman-0.0.2.dist-info/RECORD
